cryptojp/__init__.py
cryptojp/binance.py
cryptojp/bitfinex.py
cryptojp/bitflyer.py
cryptojp/btcbox.py
cryptojp/coincheck.py
cryptojp/errors.py
cryptojp/hitbtc.py
cryptojp/kraken.py
cryptojp/poloniex.py
cryptojp/quoine.py
cryptojp/realcurrency.py
cryptojp/base/__init__.py
cryptojp/base/exchange.py
cryptojp-1.0.7.dist-info/DESCRIPTION.rst
cryptojp-1.0.7.dist-info/METADATA
cryptojp-1.0.7.dist-info/RECORD
cryptojp-1.0.7.dist-info/WHEEL
cryptojp-1.0.7.dist-info/metadata.json
cryptojp-1.0.7.dist-info/top_level.txt
exchanges/__init__.py
exchanges/binance.py
exchanges/bitflyer.py
exchanges/btcbox.py
exchanges/coincheck.py
exchanges/errors.py
exchanges/hitbtc.py
exchanges/kraken.py
exchanges/okcoin.py
exchanges/poloniex.py
exchanges/quoine.py
exchanges/realcurrency.py
exchanges/zaif.py
exchanges/base/HttpHMACUtil.py
exchanges/base/HttpMD5Util.py
exchanges/base/__init__.py
exchanges/base/exchange.py
exchanges/base/initializer.py
