Metadata-Version: 2.0
Name: cryptojp
Version: 1.0.7
Summary: This is a tool for CryptoCoin Exchange api
Home-page: https://github.com/fxpgr/cryptojp
Author: Airking05
Author-email: yosuke.otosu@gmail.com
License: UNKNOWN
Keywords: bitcoin cryptocoin exchange api development
Platform: UNKNOWN
Classifier: Development Status :: 5 - Production/Stable
Classifier: Intended Audience :: Developers
Classifier: Topic :: Software Development :: Build Tools
Classifier: License :: OSI Approved :: MIT License
Classifier: Programming Language :: Python :: 2
Classifier: Programming Language :: Python :: 3
Classifier: Programming Language :: Python :: 3.4
Classifier: Programming Language :: Python :: 3.5
Classifier: Programming Language :: Python :: 3.6
Requires-Dist: requests
Requires-Dist: pyjwt
